connect/__init__.py
connect/_version.py
connect/adapters/__init__.py
connect/adapters/adapters.py
connect/evidence/__init__.py
connect/evidence/containers.py
connect/evidence/evidence.py
connect/evidence/evidence_requirement.py
connect/evidence/deepchecks_evidence/__init__.py
connect/evidence/deepchecks_evidence/containers.py
connect/evidence/deepchecks_evidence/evidence.py
connect/evidence/deepchecks_evidence/utils.py
connect/evidence/lens_evidence/__init__.py
connect/evidence/lens_evidence/containers.py
connect/evidence/lens_evidence/evidence.py
connect/evidence/lens_evidence/utils.py
connect/governance/__init__.py
connect/governance/credo_api.py
connect/governance/credo_api_client.py
connect/governance/governance.py
connect/utils/__init__.py
connect/utils/common.py
connect/utils/constants.py
connect/utils/data_scrubbing.py
connect/utils/logging.py
connect/utils/version_check.py
scripts/__init__.py
tests/__init__.py
credoai_connect-0.1.3.dist-info/LICENSE
credoai_connect-0.1.3.dist-info/METADATA
credoai_connect-0.1.3.dist-info/WHEEL
credoai_connect-0.1.3.dist-info/top_level.txt
credoai_connect-0.1.3.dist-info/RECORD
